desuko/__init__.py
desuko/__main__.py
desuko/bot.py
desuko/loader.py
desuko/modules/tutorial.py
desuko-0.1.1.dist-info/LICENSE
desuko-0.1.1.dist-info/METADATA
desuko-0.1.1.dist-info/WHEEL
desuko-0.1.1.dist-info/RECORD
