Metadata-Version: 2.1
Name: desuko
Version: 0.1.1
Summary: An extensible Discord bot, written in Python & Pycord.
Home-page: https://github.com/arichr/desuko-discord
License: MIT
Keywords: discord,async,bot,python3,discord-bot,modular,module,library
Author: Arisu Wonderland
Author-email: arisuchr@riseup.net
Requires-Python: >=3.8,<4.0
Classifier: Development Status :: 4 - Beta
Classifier: Intended Audience :: Developers
Classifier: License :: OSI Approved
Classifier: License :: OSI Approved :: MIT License
Classifier: Natural Language :: English
Classifier: Operating System :: OS Independent
Classifier: Programming Language :: Python
Classifier: Programming Language :: Python :: 3
Classifier: Programming Language :: Python :: 3.8
Classifier: Programming Language :: Python :: 3.9
Classifier: Programming Language :: Python :: 3.10
Classifier: Programming Language :: Python :: 3.11
Classifier: Programming Language :: Python :: 3
Classifier: Programming Language :: Python :: 3 :: Only
Classifier: Programming Language :: Python :: 3.10
Classifier: Programming Language :: Python :: 3.8
Classifier: Programming Language :: Python :: 3.9
Classifier: Topic :: Communications
Classifier: Topic :: Communications :: Conferencing
Classifier: Topic :: Communications :: Internet Phone
Classifier: Topic :: Internet
Classifier: Topic :: Software Development :: Libraries
Classifier: Topic :: Software Development :: Libraries :: Python Modules
Requires-Dist: PyYAML (>=6.0,<7.0)
Requires-Dist: py-cord (>=2.2.2,<3.0.0)
Project-URL: Documentation, https://arichr.github.io/desuko-discord/
Project-URL: Repository, https://github.com/arichr/desuko-discord
